lapidarist/__init__.py
lapidarist/chunk.py
lapidarist/chunk_space.py
lapidarist/document_enricher.py
lapidarist/entity_resolver.py
lapidarist/extract.py
lapidarist/knowledge_graph.py
lapidarist/read.py
lapidarist/util.py
lapidarist/vector_database.py
lapidarist/write.py
lapidarist/display/__init__.py
lapidarist/display/milvus.py
lapidarist/display/neo4j.py
lapidarist-0.0.4.dist-info/licenses/LICENSE
lapidarist-0.0.4.dist-info/METADATA
lapidarist-0.0.4.dist-info/WHEEL
lapidarist-0.0.4.dist-info/top_level.txt
lapidarist-0.0.4.dist-info/RECORD
